fast_causal_inference/__init__.py
fast_causal_inference/common/__init__.py
fast_causal_inference/common/context.py
fast_causal_inference/common/exception.py
fast_causal_inference/common/fci_logger.py
fast_causal_inference/conf/envs.yaml
fast_causal_inference/dataframe/__init__.py
fast_causal_inference/dataframe/ais_dataframe_pb2.py
fast_causal_inference/dataframe/dataframe.py
fast_causal_inference/dataframe/df_base.py
fast_causal_inference/dataframe/features.py
fast_causal_inference/dataframe/format.py
fast_causal_inference/dataframe/functions.py
fast_causal_inference/dataframe/longterm.py
fast_causal_inference/dataframe/match.py
fast_causal_inference/dataframe/provider.py
fast_causal_inference/dataframe/regression.py
fast_causal_inference/dataframe/statistics.py
fast_causal_inference/dataframe/uplift.py
fast_causal_inference/lib/__init__.py
fast_causal_inference/lib/causalforest.py
fast_causal_inference/lib/causaltree.py
fast_causal_inference/lib/estimators.py
fast_causal_inference/lib/linear_dml.py
fast_causal_inference/lib/logistic.py
fast_causal_inference/lib/longterm.py
fast_causal_inference/lib/matching.py
fast_causal_inference/lib/metrics.py
fast_causal_inference/lib/ml_spark.py
fast_causal_inference/lib/ols.py
fast_causal_inference/lib/spark_evaluation.py
fast_causal_inference/lib/spark_upliftml.py
fast_causal_inference/lib/spark_utility.py
fast_causal_inference/lib/survival.py
fast_causal_inference/lib/tmp_clickhouse_dataframe.py
fast_causal_inference/lib/tools.py
fast_causal_inference/lib/ttest.py
fast_causal_inference/util/__init__.py
fast_causal_inference/util/clickhouse_utils.py
fast_causal_inference/util/data_transformer.py
fast_causal_inference/util/formatter.py
fast_causal_inference/util/rtx.py
fast_causal_inference/util/spark.py
fast_causal_inference/util/sqlgateway.py
fast_causal_inference/util/starrocks_utils.py
fast_causal_inference/util/tdw.py
fast_causal_inference-3.0.14.dist-info/LICENSE
fast_causal_inference-3.0.14.dist-info/METADATA
fast_causal_inference-3.0.14.dist-info/WHEEL
fast_causal_inference-3.0.14.dist-info/top_level.txt
fast_causal_inference-3.0.14.dist-info/RECORD
