Metadata-Version: 2.1
Name: fast-causal-inference
Version: 3.0.14
Summary: fast causal inference package
Home-page: 
Author: ['bearlyhuang', 'fhbai', 'broccozhang']
Author-email: ['bearlyhuang@tencent.com', 'fhbai@tencent.com', 'broccozhang@tencent.com']
License: Apache License 2.0
Platform: all
Classifier: Programming Language :: Python :: 3.6
Classifier: Programming Language :: Python :: 3.7
Classifier: Programming Language :: Python :: 3.8
Requires-Python: >=3.6.0
License-File: LICENSE
Requires-Dist: pandas
Requires-Dist: matplotlib
Requires-Dist: clickhouse-driver
Requires-Dist: pyDes
Requires-Dist: seaborn
Requires-Dist: requests
Requires-Dist: graphviz
Requires-Dist: statsmodels
Requires-Dist: pyyaml
Requires-Dist: py4j>=0.10.9
Requires-Dist: scikit-Learn
Requires-Dist: pypinyin
Requires-Dist: protobuf>=3.20.0
Requires-Dist: pytest
Requires-Dist: pytest-xdist
Requires-Dist: pymysql
